llama_index/tools/cogniswitch/__init__.py
llama_index/tools/cogniswitch/base.py
flying_delta_tools_cogniswitch-0.1.0.dist-info/METADATA
flying_delta_tools_cogniswitch-0.1.0.dist-info/WHEEL
flying_delta_tools_cogniswitch-0.1.0.dist-info/RECORD
